aurora_connector/Database.py
aurora_connector/__init__.py
aurora_connector/helpers/Constants.py
aurora_connector/helpers/Exceptions.py
aurora_connector/helpers/Utils.py
aurora_connector/helpers/__init__.py
aurora_connector-0.0.4.dist-info/METADATA
aurora_connector-0.0.4.dist-info/RECORD
aurora_connector-0.0.4.dist-info/WHEEL
aurora_connector-0.0.4.dist-info/top_level.txt
