Metadata-Version: 2.1
Name: aurora-connector
Version: 0.0.4
Summary: A Python AWS Aurora Serverless Connector.
Home-page: https://github.com/johnyob/Aurora-Connector
Author: Alistair O'Brien
Author-email: alistair@duneroot.co.uk
License: UNKNOWN
Platform: UNKNOWN
Requires-Dist: boto3 (>=1.9.215)
Requires-Dist: python-dateutil
